{ "Approach":
  [ { "title": "Browser Applications"
    , "href": "browser-applications.md"
    , "when": { "published": "2017-11-12" }
    }
  , { "title": "The Theory of Some Common Object-Oriented Features"
    , "href": "theoretical-oo.md"
    }
  ]
, "Journal":
  [ { "title": "Sir, We Have a System"
    , "href": "systems.md"
    , "when": { "published": "2017-12-14" }
    }
  , { "title": "Well-Tuned Clock"
    , "href": "journal/clock.md"
    , "when": { "published": "2017-11-23" }
    }
  , { "title": "Calendar Logging"
    , "href": "journal/calendar_log.md"
    , "when": { "published": "2017-11-30" }
    }
  ]
, "Review":
  [ { "title": "Yearly Review 12017"
    , "href": "review/year-12017.md"
    , "when": { "published": "2017-12-03" }
    }
  ]
, "Reference":
  [ { "title": "How to Blag"
    , "href": "how-to-blag.md"
    , "when":
        { "published": "2017-11-02"
        , "updated": []
        }
    }
  , { "title": "How to Markdown"
    , "href": "how-to-markdown.md"
    , "when": { "published": "2017-11-03" }
    }
  , { "title": "How to Haiku"
    , "href": "how-to-haiku.md"
    , "when": { "published": "2017-12-10" }
    }
  ]
, "Curiosities":
  [ { "title": "Geometry"
    , "href": "curio/geometry.md"
    }
  , { "title": "Productivity"
    , "href": "curio/productivity.md"
    }
  , { "title": "Rationalism"
    , "href": "curio/rationalism.md"
    }
  , { "title": "Logic, Belief, Knowledge"
    , "href": "curio/logic-belief-knowledge.md"
    }
  , { "title": "Biology"
    , "href": "curio/biology.md"
    }
  ]
}
